README.md
main.py
setup.py
obfuscatron.egg-info/PKG-INFO
obfuscatron.egg-info/SOURCES.txt
obfuscatron.egg-info/dependency_links.txt
obfuscatron.egg-info/entry_points.txt
obfuscatron.egg-info/requires.txt
obfuscatron.egg-info/top_level.txt