Metadata-Version: 2.1
Name: obfuscatron
Version: 1.0.0
Summary: Encrypt data by storing it within a Python script that pretends to just be "obfuscated"
Home-page: http://github.com/Pebaz/obfuscatron
Author: http://github.com/Pebaz
License: MIT
Platform: UNKNOWN
